[
  {
    "id": "kt-ch20-l1",
    "chapter": 20,
    "lessonInChapter": 1,
    "segmentType": "main-story",
    "storyId": "enormous-turnip",
    "storyBeat": "老爺爺種大蘿蔔 — 長得越來越大",
    "questions": [
      {
        "type": "tap-pairs",
        "id": "kt-ch20-l1-q1",
        "level": "A2",
        "difficulty": "easy",
        "speaker": "narrator",
        "sentence": "Here are 4 words you will meet in tonight's story.",
        "pairs": [
          {
            "left": "爺爺",
            "right": "grandpa"
          },
          {
            "left": "種子",
            "right": "seed"
          },
          {
            "left": "水",
            "right": "water"
          },
          {
            "left": "長大",
            "right": "grow"
          }
        ],
        "explanationZh": "本節新單字 (左中右英):\n🔑 grandpa = 爺爺\n🔑 seed = 種子\n🔑 water = 水\n🔑 grow = 長大\n背熟這 4 個字,故事就會輕鬆聽懂。",
        "tags": [
          "story",
          "ch20",
          "enormous-turnip",
          "vocab",
          "intro"
        ]
      },
      {
        "type": "narration",
        "id": "kt-ch20-l1-q2",
        "level": "A2",
        "difficulty": "easy",
        "speaker": "narrator",
        "sentence": "Grandpa plants a small turnip seed in his garden.",
        "explanationZh": "爺爺在園子裡蹲下身子,把一顆小小的蘿蔔種子輕輕埋進土裡。",
        "tags": [
          "story",
          "ch20",
          "enormous-turnip"
        ]
      },
      {
        "type": "narration",
        "id": "kt-ch20-l1-q3",
        "level": "A2",
        "difficulty": "easy",
        "speaker": "narrator",
        "sentence": "Every morning, he gives the seed water.",
        "explanationZh": "每天清晨,爺爺都會來澆水。一天都沒有少過。",
        "tags": [
          "story",
          "ch20",
          "enormous-turnip"
        ]
      },
      {
        "type": "listen-tf",
        "id": "kt-ch20-l1-q4",
        "level": "A2",
        "difficulty": "medium",
        "speaker": "narrator",
        "sentence": "Grandpa sings to the seed every day. He never forgets.",
        "questionEn": "Does Grandpa care about this turnip?",
        "options": [
          "Yes",
          "No"
        ],
        "correctIndex": 0,
        "explanationZh": "每天唱歌、從來不忘——這樣的爺爺,怎麼可能不在乎呢?答案是 Yes 囉!",
        "tags": [
          "story",
          "ch20",
          "enormous-turnip",
          "inference"
        ],
        "sentenceZh": "爺爺每天對著種子唱歌,從來不忘記。"
      },
      {
        "type": "narration",
        "id": "kt-ch20-l1-q5",
        "level": "A2",
        "difficulty": "easy",
        "speaker": "narrator",
        "sentence": "A green leaf comes up. Then more leaves come up.",
        "explanationZh": "一片綠葉冒出來。然後更多葉子冒出來。",
        "tags": [
          "story",
          "ch20",
          "enormous-turnip"
        ]
      },
      {
        "type": "listen-mc",
        "id": "kt-ch20-l1-q6",
        "level": "A2",
        "difficulty": "easy",
        "speaker": "narrator",
        "sentence": "Week by week, the turnip gets larger than the others.",
        "question": "How is the turnip growing?",
        "options": [
          "staying small",
          "getting much bigger",
          "turning bright red",
          "falling on its side"
        ],
        "optionsZh": [
          "還是很小",
          "越來越大",
          "變成亮紅色",
          "倒向一邊"
        ],
        "correctIndex": 1,
        "explanationZh": "「一週又一週」、「比其他的大」,兩個線索疊起來,答案就是:越來越大。",
        "tags": [
          "story",
          "ch20",
          "enormous-turnip"
        ],
        "subSkill": "detail",
        "sentenceZh": "一週又一週,蘿蔔長得比其他的都大。"
      },
      {
        "type": "narration",
        "id": "kt-ch20-l1-q7",
        "level": "A2",
        "difficulty": "easy",
        "speaker": "narrator",
        "sentence": "The turnip pushes up the dirt. The top is round and yellow.",
        "explanationZh": "蘿蔔把土頂起來。頂上圓圓黃黃的。",
        "tags": [
          "story",
          "ch20",
          "enormous-turnip"
        ]
      },
      {
        "type": "emoji-pick",
        "id": "kt-ch20-l1-q8",
        "level": "A2",
        "difficulty": "easy",
        "speaker": "narrator",
        "sentence": "How big is the turnip now?",
        "question": "How big?",
        "options": [
          "🥬 small leaf",
          "🥕 normal size",
          "🎃 very big",
          "🌱 just a sprout"
        ],
        "optionsZh": [
          "小葉子",
          "一般大",
          "非常大",
          "剛冒芽"
        ],
        "correctIndex": 2,
        "explanationZh": "前幾句說它比別的都大——那當然是「非常大」囉!",
        "tags": [
          "story",
          "ch20",
          "enormous-turnip",
          "hook"
        ],
        "subSkill": "vocab",
        "sentenceZh": "現在的蘿蔔有多大?"
      },
      {
        "type": "listen-mc",
        "id": "kt-ch20-l1-q9",
        "level": "A2",
        "difficulty": "easy",
        "speaker": "narrator",
        "sentence": "Grandpa cannot put his arms all the way around the top.",
        "question": "Why is the turnip a problem?",
        "options": [
          "too small to find",
          "too soft",
          "wrong color",
          "too big to hug"
        ],
        "optionsZh": [
          "太小找不到",
          "太軟",
          "顏色不對",
          "太大抱不住"
        ],
        "correctIndex": 3,
        "explanationZh": "手抱不過去,代表它大得不得了——所以問題在於「太大抱不住」。",
        "tags": [
          "story",
          "ch20",
          "enormous-turnip"
        ],
        "subSkill": "detail",
        "sentenceZh": "爺爺的雙手抱不住蘿蔔頂端。"
      },
      {
        "type": "comprehension",
        "id": "kt-ch20-l1-q10",
        "level": "A2",
        "difficulty": "medium",
        "speaker": "narrator",
        "sentence": "A tiny seed has grown into the biggest turnip in the village.",
        "question": "What is this scene mainly showing?",
        "options": [
          "something growing way past normal",
          "a small flower in the garden bed",
          "a busy market day in the village",
          "snow falling over the village"
        ],
        "optionsZh": [
          "長到超過一般大小",
          "花圃裡的一朵小花",
          "村裡熱鬧的市集日",
          "雪落在村子上"
        ],
        "correctIndex": 0,
        "explanationZh": "這一幕在說什麼?就是一顆小種子竟然長到超出一般大小,比全村的蘿蔔都大!",
        "tags": [
          "story",
          "ch20",
          "enormous-turnip",
          "gist"
        ],
        "subSkill": "gist",
        "sentenceZh": "一顆小種子,長成了全村最大的蘿蔔。"
      },
      {
        "type": "narration",
        "id": "kt-ch20-l1-q11",
        "level": "A2",
        "difficulty": "easy",
        "speaker": "narrator",
        "sentence": "It is the biggest turnip in the village. Grandpa looks at it. \"Time to pull it out...\"",
        "explanationZh": "這是全村最大的蘿蔔。爺爺看著它,輕聲說:「該把它拔出來了……」",
        "tags": [
          "story",
          "ch20",
          "enormous-turnip"
        ]
      },
      {
        "type": "comprehension",
        "id": "kt-ch20-l1-x1",
        "level": "A2",
        "difficulty": "easy",
        "speaker": "narrator",
        "sentence": "Grandpa plants a small turnip seed and waters it each day.",
        "question": "What two actions help the seed grow?",
        "options": [
          "singing near it at night",
          "caring for it every day",
          "digging it up twice a week",
          "covering it with heavy stones"
        ],
        "optionsZh": [
          "每晚在旁邊唱歌",
          "每天照顧它",
          "每週挖兩次",
          "用重石壓住"
        ],
        "correctIndex": 1,
        "explanationZh": "爺爺每天種下去、每天澆水——這就是「caring for it every day」!",
        "sentenceZh": "爺爺種下一顆小蘿蔔種子,每天都澆水。",
        "tags": [
          "story",
          "ch20",
          "enormous-turnip",
          "sequence"
        ],
        "subSkill": "detail"
      },
      {
        "type": "listen-tf",
        "id": "kt-ch20-l1-x2",
        "level": "A2",
        "difficulty": "medium",
        "speaker": "narrator",
        "sentence": "The turnip grew and grew until it was the biggest in the village.",
        "questionEn": "Did the turnip stay small after Grandpa watered it?",
        "options": [
          "Yes",
          "No"
        ],
        "correctIndex": 1,
        "explanationZh": "「grew and grew」是越長越大——哪裡是待著不動?答案是 No,它長大了。",
        "sentenceZh": "蘿蔔越長越大,直到成了村裡最大的。",
        "tags": [
          "story",
          "ch20",
          "enormous-turnip",
          "inference"
        ]
      },
      {
        "type": "comprehension",
        "id": "kt-ch20-l1-x3",
        "level": "A2",
        "difficulty": "easy",
        "speaker": "narrator",
        "sentence": "A green leaf came up first, then more leaves followed one by one.",
        "question": "What appeared from the ground before anything else?",
        "options": [
          "some small flowers",
          "a thick yellow root",
          "the first tiny leaf",
          "a furry little bug"
        ],
        "optionsZh": [
          "一些小花",
          "一條粗黃色根",
          "第一片小葉子",
          "一隻毛茸茸的小蟲"
        ],
        "correctIndex": 2,
        "explanationZh": "「A green leaf came up first」就是說葉子最先出來!",
        "sentenceZh": "先長出一片綠葉,然後更多葉子一片一片地跟著出來。",
        "tags": [
          "story",
          "ch20",
          "enormous-turnip",
          "sequence"
        ],
        "subSkill": "detail"
      },
      {
        "type": "tap-pairs",
        "id": "kt-ch20-l1-x4",
        "level": "A2",
        "difficulty": "easy",
        "speaker": "narrator",
        "sentence": "Match the words from this lesson.",
        "pairs": [
          {
            "left": "葉子",
            "right": "leaf"
          },
          {
            "left": "土",
            "right": "dirt"
          },
          {
            "left": "大",
            "right": "big"
          },
          {
            "left": "圓",
            "right": "round"
          }
        ],
        "explanationZh": "🔑 leaf = 葉子\n🔑 dirt = 土\n🔑 big = 大\n🔑 round = 圓\n這 4 個字在故事裡都出現了,配對一下吧!",
        "tags": [
          "story",
          "ch20",
          "enormous-turnip",
          "vocab"
        ]
      },
      {
        "type": "comprehension",
        "id": "kt-ch20-l1-x5",
        "level": "A2",
        "difficulty": "medium",
        "speaker": "narrator",
        "sentence": "Grandpa sang to the seed every day and never forgot.",
        "question": "Why does Grandpa sing to the seed?",
        "options": [
          "he forgot the words",
          "he has nothing to do",
          "it scares away birds",
          "he loves caring for it"
        ],
        "optionsZh": [
          "他忘記歌詞了",
          "他無聊沒事做",
          "嚇走鳥兒",
          "他喜歡照顧它"
        ],
        "correctIndex": 3,
        "explanationZh": "每天唱歌又從不忘記——這就是真心「喜歡照顧它」的表現喔!",
        "sentenceZh": "爺爺每天對著種子唱歌,從來不忘記。",
        "tags": [
          "story",
          "ch20",
          "enormous-turnip"
        ],
        "subSkill": "inference"
      },
      {
        "type": "grammar-mc",
        "id": "kt-ch20-l1-x6",
        "level": "A2",
        "difficulty": "easy",
        "speaker": "narrator",
        "sentence": "Every morning, he ___ the seed water.",
        "question": "Choose the correct word.",
        "options": [
          "gives",
          "give",
          "giving",
          "given"
        ],
        "optionsZh": [
          "gives",
          "give",
          "giving",
          "given"
        ],
        "correctIndex": 0,
        "explanationZh": "「he」是第三人稱單數,現在式動詞要加 -s → gives。奶奶說:he gives 才對喔!",
        "sentenceZh": "每天早上,他給種子澆水。",
        "tags": [
          "story",
          "ch20",
          "enormous-turnip",
          "grammar"
        ],
        "subSkill": "function"
      },
      {
        "type": "emoji-pick",
        "id": "kt-ch20-l1-x7",
        "level": "A2",
        "difficulty": "easy",
        "speaker": "narrator",
        "sentence": "What colour is the top of the turnip?",
        "question": "What colour?",
        "options": [
          "🟢 green",
          "🟡 yellow",
          "🔴 red",
          "🔵 blue"
        ],
        "optionsZh": [
          "綠色",
          "黃色",
          "紅色",
          "藍色"
        ],
        "correctIndex": 1,
        "explanationZh": "「The top is round and yellow」——頂端是黃色的喔!",
        "sentenceZh": "蘿蔔頂端是什麼顏色?",
        "tags": [
          "story",
          "ch20",
          "enormous-turnip",
          "hook"
        ],
        "subSkill": "vocab"
      },
      {
        "type": "listen-tf",
        "id": "kt-ch20-l1-x8",
        "level": "A2",
        "difficulty": "medium",
        "speaker": "narrator",
        "sentence": "Grandpa cannot put his arms all the way around the top.",
        "questionEn": "Is the turnip easy for one person to carry?",
        "options": [
          "Yes",
          "No"
        ],
        "correctIndex": 1,
        "explanationZh": "手抱不過去——哪有可能容易拿呢?答案是 No,太大了!",
        "sentenceZh": "爺爺的雙手抱不住蘿蔔的頂端。",
        "tags": [
          "story",
          "ch20",
          "enormous-turnip",
          "inference"
        ]
      }
    ]
  },
  {
    "id": "kt-ch20-l2",
    "chapter": 20,
    "lessonInChapter": 2,
    "segmentType": "main-story",
    "storyId": "enormous-turnip",
    "storyBeat": "想拔起來 — 拔不動!",
    "questions": [
      {
        "type": "tap-pairs",
        "id": "kt-ch20-l2-q1",
        "level": "A2",
        "difficulty": "easy",
        "speaker": "narrator",
        "sentence": "Here are 4 words you will meet in tonight's story.",
        "pairs": [
          {
            "left": "拉",
            "right": "pull"
          },
          {
            "left": "葉子",
            "right": "leaves"
          },
          {
            "left": "手",
            "right": "hands"
          },
          {
            "left": "動",
            "right": "move"
          }
        ],
        "explanationZh": "本節新單字 (左中右英):\n🔑 pull = 拉\n🔑 leaves = 葉子\n🔑 hands = 手\n🔑 move = 動\n背熟這 4 個字,故事就會輕鬆聽懂。",
        "tags": [
          "story",
          "ch20",
          "enormous-turnip",
          "vocab",
          "intro"
        ]
      },
      {
        "type": "narration",
        "id": "kt-ch20-l2-q2",
        "level": "A2",
        "difficulty": "easy",
        "speaker": "narrator",
        "sentence": "Grandpa walks into the garden. He puts down his hat.",
        "explanationZh": "爺爺走進園子,把帽子輕輕放在一邊——要認真工作了。",
        "tags": [
          "story",
          "ch20",
          "enormous-turnip"
        ]
      },
      {
        "type": "narration",
        "id": "kt-ch20-l2-q3",
        "level": "A2",
        "difficulty": "easy",
        "speaker": "narrator",
        "sentence": "He holds the green leaves with both hands.",
        "explanationZh": "爺爺用兩隻手緊緊抓住葉子,準備用力拉。",
        "tags": [
          "story",
          "ch20",
          "enormous-turnip"
        ]
      },
      {
        "type": "listen-tf",
        "id": "kt-ch20-l2-q4",
        "level": "A2",
        "difficulty": "medium",
        "speaker": "narrator",
        "sentence": "Grandpa pulls hard. He pulls again. His face turns red.",
        "questionEn": "Is Grandpa using a lot of strength?",
        "options": [
          "Yes",
          "No"
        ],
        "correctIndex": 0,
        "explanationZh": "一拉再拉,臉都紅了——這不是費盡全力是什麼呀?答案是 Yes!",
        "tags": [
          "story",
          "ch20",
          "enormous-turnip",
          "inference"
        ],
        "sentenceZh": "爺爺用力拉,又拉了一次。他的臉變得紅紅的。"
      },
      {
        "type": "listen-mc",
        "id": "kt-ch20-l2-q5",
        "level": "A2",
        "difficulty": "easy",
        "speaker": "narrator",
        "sentence": "The turnip stays right where it is. Not one bit out of the dirt.",
        "question": "What happens to the turnip?",
        "options": [
          "pops out fast",
          "breaks in half",
          "stays in the ground",
          "bends sideways"
        ],
        "optionsZh": [
          "一下就出來",
          "斷成兩半",
          "完全沒動",
          "彎下去"
        ],
        "correctIndex": 2,
        "explanationZh": "「一點都沒從土裡出來」——也就是完全沒動嘛!",
        "tags": [
          "story",
          "ch20",
          "enormous-turnip"
        ],
        "subSkill": "detail",
        "sentenceZh": "蘿蔔就待在原地,一點都沒從土裡出來。"
      },
      {
        "type": "narration",
        "id": "kt-ch20-l2-q6",
        "level": "A2",
        "difficulty": "easy",
        "speaker": "narrator",
        "sentence": "Grandpa sits down on the dirt. He looks at his hands.",
        "explanationZh": "爺爺累了,坐到土上。他看著自己的手,心裡大概很不是滋味。",
        "tags": [
          "story",
          "ch20",
          "enormous-turnip"
        ]
      },
      {
        "type": "emoji-pick",
        "id": "kt-ch20-l2-q7",
        "level": "A2",
        "difficulty": "easy",
        "speaker": "narrator",
        "sentence": "How does Grandpa feel right now?",
        "question": "How does he feel?",
        "options": [
          "😴 getting very sleepy",
          "🥳 cheerful and merry",
          "😡 starting to feel mad",
          "😅 tired and stuck"
        ],
        "optionsZh": [
          "快要睡著了",
          "開心又愉快",
          "開始覺得生氣",
          "又累又卡住"
        ],
        "correctIndex": 3,
        "explanationZh": "拉不動坐下來,那當然是「又累又卡住」啦!",
        "tags": [
          "story",
          "ch20",
          "enormous-turnip",
          "hook"
        ],
        "subSkill": "vocab",
        "sentenceZh": "爺爺現在覺得怎麼樣?"
      },
      {
        "type": "narration",
        "id": "kt-ch20-l2-q8",
        "level": "A2",
        "difficulty": "easy",
        "speaker": "narrator",
        "sentence": "He pulls one more time. His hands slip off the leaves.",
        "explanationZh": "他再試了一次——結果手從葉子上滑開了,更挫折了。",
        "tags": [
          "story",
          "ch20",
          "enormous-turnip"
        ]
      },
      {
        "type": "listen-mc",
        "id": "kt-ch20-l2-q9",
        "level": "A2",
        "difficulty": "easy",
        "speaker": "narrator",
        "sentence": "One person's hands are too few. The turnip is much too big.",
        "question": "Why can't Grandpa pull it out?",
        "options": [
          "one person is not enough",
          "the turnip is too small",
          "the dirt is too wet today",
          "the leaves are gone"
        ],
        "optionsZh": [
          "一個人不夠",
          "蘿蔔太小",
          "今天的土太濕",
          "葉子沒了"
        ],
        "correctIndex": 0,
        "explanationZh": "「一個人手太少」加上「蘿蔔太大」,加在一起的意思就是:一個人不夠啦!",
        "tags": [
          "story",
          "ch20",
          "enormous-turnip"
        ],
        "subSkill": "detail",
        "sentenceZh": "一個人的手太少了。蘿蔔實在太大。"
      },
      {
        "type": "comprehension",
        "id": "kt-ch20-l2-q10",
        "level": "A2",
        "difficulty": "medium",
        "speaker": "narrator",
        "sentence": "Grandpa looks back at the house. Someone else lives with him.",
        "question": "What is Grandpa thinking now?",
        "options": [
          "give up and go in",
          "call someone for help",
          "eat the leaves",
          "plant a new seed"
        ],
        "optionsZh": [
          "放棄回家",
          "叫人來幫忙",
          "吃葉子",
          "種新種子"
        ],
        "correctIndex": 1,
        "explanationZh": "回頭看屋子,屋裡還有別人——這是在想什麼?當然是想叫人來幫忙囉!",
        "tags": [
          "story",
          "ch20",
          "enormous-turnip"
        ],
        "subSkill": "inference",
        "sentenceZh": "爺爺回頭看了一眼屋子。屋裡還有別人住著呢。"
      },
      {
        "type": "narration",
        "id": "kt-ch20-l2-q11",
        "level": "A2",
        "difficulty": "easy",
        "speaker": "narrator",
        "sentence": "Grandpa stands up. \"I cannot do this alone,\" he says. \"I need help...\"",
        "explanationZh": "爺爺站起身,說:「我一個人做不到,我需要幫忙……」",
        "tags": [
          "story",
          "ch20",
          "enormous-turnip"
        ]
      },
      {
        "type": "comprehension",
        "id": "kt-ch20-l2-x1",
        "level": "A2",
        "difficulty": "easy",
        "speaker": "narrator",
        "sentence": "Grandpa holds the green leaves and pulls with all his strength.",
        "question": "What does Grandpa grab to pull the turnip?",
        "options": [
          "a piece of rope",
          "the yellow top",
          "its green leaves",
          "a long stick"
        ],
        "optionsZh": [
          "一條繩子",
          "黃色頂端",
          "綠葉子",
          "一根長棍"
        ],
        "correctIndex": 2,
        "explanationZh": "「holds the green leaves」——爺爺抓的就是綠葉子,用力往上拉!",
        "sentenceZh": "爺爺抓住綠葉子,用全力拉。",
        "tags": [
          "story",
          "ch20",
          "enormous-turnip"
        ],
        "subSkill": "detail"
      },
      {
        "type": "listen-tf",
        "id": "kt-ch20-l2-x2",
        "level": "A2",
        "difficulty": "medium",
        "speaker": "narrator",
        "sentence": "He pulls again and again but the turnip does not move at all.",
        "questionEn": "Did Grandpa give up after the first try?",
        "options": [
          "Yes",
          "No"
        ],
        "correctIndex": 1,
        "explanationZh": "「again and again」——一再一再地拉,沒有放棄。答案是 No,他繼續試!",
        "sentenceZh": "他一拉再拉,但蘿蔔一點都沒動。",
        "tags": [
          "story",
          "ch20",
          "enormous-turnip",
          "inference"
        ]
      },
      {
        "type": "comprehension",
        "id": "kt-ch20-l2-x3",
        "level": "A2",
        "difficulty": "easy",
        "speaker": "narrator",
        "sentence": "He pulls one more time. His hands slip off the leaves.",
        "question": "What happens to his hands?",
        "options": [
          "grab a long vine",
          "hold the leaves tight",
          "get stuck in dirt",
          "slide off the leaves"
        ],
        "optionsZh": [
          "抓住一條長藤",
          "緊緊抓住葉子",
          "卡在土裡",
          "從葉子上滑掉"
        ],
        "correctIndex": 3,
        "explanationZh": "「hands slip off」——手從葉子上滑掉了!試了那麼多次手都麻了。",
        "sentenceZh": "他再拉了一次,手從葉子上滑掉了。",
        "tags": [
          "story",
          "ch20",
          "enormous-turnip"
        ],
        "subSkill": "detail"
      },
      {
        "type": "tap-pairs",
        "id": "kt-ch20-l2-x4",
        "level": "A2",
        "difficulty": "easy",
        "speaker": "narrator",
        "sentence": "Match the words from this lesson.",
        "pairs": [
          {
            "left": "拉",
            "right": "pull"
          },
          {
            "left": "用力",
            "right": "strength"
          },
          {
            "left": "臉",
            "right": "face"
          },
          {
            "left": "地",
            "right": "ground"
          }
        ],
        "explanationZh": "🔑 pull = 拉\n🔑 strength = 用力\n🔑 face = 臉\n🔑 ground = 地\n這 4 個字幫你記住這節的重點!",
        "tags": [
          "story",
          "ch20",
          "enormous-turnip",
          "vocab"
        ]
      },
      {
        "type": "emoji-pick",
        "id": "kt-ch20-l2-x5",
        "level": "A2",
        "difficulty": "easy",
        "speaker": "narrator",
        "sentence": "Grandpa sat on the dirt, wiping sweat from his forehead.",
        "question": "Which emoji best shows how Grandpa feels?",
        "options": [
          "😤 worn out",
          "😊 delighted",
          "😴 bored",
          "😋 satisfied"
        ],
        "optionsZh": [
          "精疲力竭",
          "開心",
          "無聊",
          "心滿意足"
        ],
        "correctIndex": 0,
        "explanationZh": "擦汗、坐在地上——爺爺累壞了,「worn out」最貼切。",
        "sentenceZh": "爺爺坐在地上,用手擦去額頭上的汗水。",
        "tags": [
          "story",
          "ch20",
          "enormous-turnip",
          "character"
        ],
        "subSkill": "inference"
      },
      {
        "type": "comprehension",
        "id": "kt-ch20-l2-x6",
        "level": "A2",
        "difficulty": "medium",
        "speaker": "narrator",
        "sentence": "One person's hands are too few. The turnip is much too big.",
        "question": "What does Grandpa understand now?",
        "options": [
          "the seed was too old",
          "he needs more hands",
          "the leaves are rotten",
          "he dug too shallow"
        ],
        "optionsZh": [
          "種子太老了",
          "他需要更多手",
          "葉子爛掉了",
          "他挖太淺了"
        ],
        "correctIndex": 1,
        "explanationZh": "「hands are too few」——手不夠——所以明白「需要更多手(幫忙的人)」!",
        "sentenceZh": "一個人的手太少了。蘿蔔實在太大。",
        "tags": [
          "story",
          "ch20",
          "enormous-turnip"
        ],
        "subSkill": "inference"
      },
      {
        "type": "grammar-mc",
        "id": "kt-ch20-l2-x7",
        "level": "A2",
        "difficulty": "easy",
        "speaker": "narrator",
        "sentence": "Grandpa ___ down on the dirt after pulling so hard.",
        "question": "Choose the correct word.",
        "options": [
          "sit",
          "sits",
          "sat",
          "sitting"
        ],
        "optionsZh": [
          "sit",
          "sits",
          "sat",
          "sitting"
        ],
        "correctIndex": 2,
        "explanationZh": "這句在描述故事裡「已經發生的事」,所以用過去式 sat(sit 的過去式)。奶奶說故事都用過去式喔!",
        "sentenceZh": "爺爺拉得那麼用力之後坐到土上。",
        "tags": [
          "story",
          "ch20",
          "enormous-turnip",
          "grammar"
        ],
        "subSkill": "function"
      },
      {
        "type": "listen-tf",
        "id": "kt-ch20-l2-x8",
        "level": "A2",
        "difficulty": "medium",
        "speaker": "narrator",
        "sentence": "Grandpa looks back at the house and thinks about asking for help.",
        "questionEn": "Is Grandpa ready to ask someone for help?",
        "options": [
          "Yes",
          "No"
        ],
        "correctIndex": 0,
        "explanationZh": "回頭看屋子、想著幫忙——這正是他在考慮「找人幫忙」的樣子。答案是 Yes!",
        "sentenceZh": "爺爺回頭看了一眼屋子,心裡想著要請人幫忙。",
        "tags": [
          "story",
          "ch20",
          "enormous-turnip",
          "inference"
        ]
      }
    ]
  },
  {
    "id": "kt-ch20-l3",
    "chapter": 20,
    "lessonInChapter": 3,
    "segmentType": "main-story",
    "storyId": "enormous-turnip",
    "storyBeat": "叫奶奶來幫 — 還是拔不動",
    "questions": [
      {
        "type": "tap-pairs",
        "id": "kt-ch20-l3-q1",
        "level": "A2",
        "difficulty": "easy",
        "speaker": "narrator",
        "sentence": "Here are 4 words you will meet in tonight's story.",
        "pairs": [
          {
            "left": "奶奶",
            "right": "grandma"
          },
          {
            "left": "叫",
            "right": "call"
          },
          {
            "left": "幫忙",
            "right": "help"
          },
          {
            "left": "兩個",
            "right": "both"
          }
        ],
        "explanationZh": "本節新單字 (左中右英):\n🔑 grandma = 奶奶\n🔑 call = 叫\n🔑 help = 幫忙\n🔑 both = 兩個\n背熟這 4 個字,故事就會輕鬆聽懂。",
        "tags": [
          "story",
          "ch20",
          "enormous-turnip",
          "vocab",
          "intro"
        ]
      },
      {
        "type": "narration",
        "id": "kt-ch20-l3-q2",
        "level": "A2",
        "difficulty": "easy",
        "speaker": "narrator",
        "sentence": "Grandpa calls toward the kitchen. \"Grandma, come help me!\"",
        "explanationZh": "爺爺轉向廚房大叫:「奶奶,快來幫我!」",
        "tags": [
          "story",
          "ch20",
          "enormous-turnip"
        ]
      },
      {
        "type": "narration",
        "id": "kt-ch20-l3-q3",
        "level": "A2",
        "difficulty": "easy",
        "speaker": "narrator",
        "sentence": "Grandma comes out, drying her hands on her apron.",
        "explanationZh": "奶奶從廚房走出來,一邊用圍裙擦手——她剛才還在忙呢。",
        "tags": [
          "story",
          "ch20",
          "enormous-turnip"
        ]
      },
      {
        "type": "listen-tf",
        "id": "kt-ch20-l3-q4",
        "level": "A2",
        "difficulty": "medium",
        "speaker": "narrator",
        "sentence": "She walks fast. She does not ask any questions first.",
        "questionEn": "Does Grandma want to help right away?",
        "options": [
          "Yes",
          "No"
        ],
        "correctIndex": 0,
        "explanationZh": "走得快、連問都不問就衝出來——這樣的奶奶,當然是馬上想幫忙啦!答案是 Yes。",
        "tags": [
          "story",
          "ch20",
          "enormous-turnip",
          "inference"
        ],
        "sentenceZh": "她走得很快,一個問題都沒問就來了。"
      },
      {
        "type": "listen-mc",
        "id": "kt-ch20-l3-q5",
        "level": "A2",
        "difficulty": "easy",
        "speaker": "narrator",
        "sentence": "Grandma holds the back of Grandpa's coat with her two hands.",
        "question": "Where does Grandma hold on?",
        "options": [
          "around the turnip top",
          "in her own apron pocket",
          "against the garden fence",
          "on the man in front of her"
        ],
        "optionsZh": [
          "蘿蔔頂",
          "她自己圍裙口袋",
          "園子圍籬",
          "前面那個人"
        ],
        "correctIndex": 3,
        "explanationZh": "抓爺爺外套後面,也就是抓住前面那個人,然後一起拉!",
        "tags": [
          "story",
          "ch20",
          "enormous-turnip"
        ],
        "subSkill": "detail",
        "sentenceZh": "奶奶用兩隻手抓住爺爺外套的後面。"
      },
      {
        "type": "narration",
        "id": "kt-ch20-l3-q6",
        "level": "A2",
        "difficulty": "easy",
        "speaker": "narrator",
        "sentence": "Grandpa pulls the turnip. Grandma pulls Grandpa.",
        "explanationZh": "爺爺拉蘿蔔。奶奶拉爺爺。一前一後,串成一條線!",
        "tags": [
          "story",
          "ch20",
          "enormous-turnip"
        ]
      },
      {
        "type": "emoji-pick",
        "id": "kt-ch20-l3-q7",
        "level": "A2",
        "difficulty": "easy",
        "speaker": "narrator",
        "sentence": "How many people are pulling now?",
        "question": "How many?",
        "options": [
          "2️⃣ two",
          "1️⃣ one",
          "3️⃣ three",
          "4️⃣ four"
        ],
        "optionsZh": [
          "兩個",
          "一個",
          "三個",
          "四個"
        ],
        "correctIndex": 0,
        "explanationZh": "爺爺加奶奶——一加一等於兩個人!",
        "tags": [
          "story",
          "ch20",
          "enormous-turnip",
          "hook"
        ],
        "subSkill": "vocab",
        "sentenceZh": "現在有幾個人在拉?"
      },
      {
        "type": "narration",
        "id": "kt-ch20-l3-q8",
        "level": "A2",
        "difficulty": "easy",
        "speaker": "narrator",
        "sentence": "They both pull. They count out loud. One, two, pull!",
        "explanationZh": "兩個人一起拉,還一邊數:一、二——拉!",
        "tags": [
          "story",
          "ch20",
          "enormous-turnip"
        ]
      },
      {
        "type": "listen-mc",
        "id": "kt-ch20-l3-q9",
        "level": "A2",
        "difficulty": "easy",
        "speaker": "narrator",
        "sentence": "Even with two pulling together, the turnip stays in the dirt.",
        "question": "What happens with two pullers?",
        "options": [
          "comes out easy",
          "still stuck deep",
          "breaks the leaves",
          "bends sideways"
        ],
        "optionsZh": [
          "一下就出來",
          "還是卡在土裡",
          "弄斷葉子",
          "歪一邊"
        ],
        "correctIndex": 1,
        "explanationZh": "兩個人一起拉了,蘿蔔還是沒出來——也就是說,還是卡著。",
        "tags": [
          "story",
          "ch20",
          "enormous-turnip"
        ],
        "subSkill": "detail",
        "sentenceZh": "就算兩個人一起拉,蘿蔔還是待在土裡不動。"
      },
      {
        "type": "comprehension",
        "id": "kt-ch20-l3-q10",
        "level": "A2",
        "difficulty": "medium",
        "speaker": "narrator",
        "sentence": "One person tried and could not. Two together tried and still cannot.",
        "question": "What is this scene mainly showing?",
        "options": [
          "the big turnip has disappeared",
          "Grandma is too small to help at all",
          "help is needed but two is not enough",
          "Grandpa is angry and stops trying"
        ],
        "optionsZh": [
          "大蘿蔔不見了",
          "奶奶太小幫不上忙",
          "需要幫忙 + 兩個不夠",
          "爺爺生氣不拉了"
        ],
        "correctIndex": 2,
        "explanationZh": "一個不行、兩個還是不行——這一幕在說:需要更多幫手,兩個人不夠!",
        "tags": [
          "story",
          "ch20",
          "enormous-turnip",
          "gist"
        ],
        "subSkill": "gist",
        "sentenceZh": "一個人試過沒辦法。兩個人一起試還是沒辦法。"
      },
      {
        "type": "narration",
        "id": "kt-ch20-l3-q11",
        "level": "A2",
        "difficulty": "easy",
        "speaker": "narrator",
        "sentence": "Two is not enough. Grandma looks at Grandpa. \"Who else can we ask?\"",
        "explanationZh": "兩個還不夠。奶奶看著爺爺:「我們還能叫誰?」",
        "tags": [
          "story",
          "ch20",
          "enormous-turnip"
        ]
      },
      {
        "type": "comprehension",
        "id": "kt-ch20-l3-x1",
        "level": "A2",
        "difficulty": "easy",
        "speaker": "narrator",
        "sentence": "Grandpa called Grandma and she came out drying her hands.",
        "question": "What was Grandma doing just before she came out?",
        "options": [
          "reading a long book",
          "sleeping in her chair",
          "singing in the yard",
          "working inside"
        ],
        "optionsZh": [
          "讀一本長書",
          "坐椅子睡覺",
          "在院子唱歌",
          "在裡面做事"
        ],
        "correctIndex": 3,
        "explanationZh": "「drying her hands」——擦著手出來,說明她剛剛在裡面做事(洗碗/煮菜)。",
        "sentenceZh": "爺爺叫了奶奶,她擦著手走出來。",
        "tags": [
          "story",
          "ch20",
          "enormous-turnip"
        ],
        "subSkill": "inference"
      },
      {
        "type": "listen-tf",
        "id": "kt-ch20-l3-x2",
        "level": "A2",
        "difficulty": "medium",
        "speaker": "narrator",
        "sentence": "She walks fast and does not ask any questions first.",
        "questionEn": "Did Grandma stop to ask what was happening before running out?",
        "options": [
          "Yes",
          "No"
        ],
        "correctIndex": 1,
        "explanationZh": "「does not ask any questions」——一個問題都沒問就衝出去。答案是 No,她直接幫忙!",
        "sentenceZh": "她走得很快,一個問題都沒問。",
        "tags": [
          "story",
          "ch20",
          "enormous-turnip",
          "inference"
        ]
      },
      {
        "type": "tap-pairs",
        "id": "kt-ch20-l3-x3",
        "level": "A2",
        "difficulty": "easy",
        "speaker": "narrator",
        "sentence": "Match the words from this lesson.",
        "pairs": [
          {
            "left": "外套",
            "right": "coat"
          },
          {
            "left": "數",
            "right": "count"
          },
          {
            "left": "一起",
            "right": "together"
          },
          {
            "left": "喊",
            "right": "call"
          }
        ],
        "explanationZh": "🔑 coat = 外套\n🔑 count = 數\n🔑 together = 一起\n🔑 call = 喊\n這 4 個字在這節故事裡都很重要!",
        "tags": [
          "story",
          "ch20",
          "enormous-turnip",
          "vocab"
        ]
      },
      {
        "type": "comprehension",
        "id": "kt-ch20-l3-x4",
        "level": "A2",
        "difficulty": "easy",
        "speaker": "narrator",
        "sentence": "Grandpa pulls the turnip. Grandma pulls Grandpa.",
        "question": "Who holds the back of Grandpa's coat?",
        "options": [
          "Grandma does",
          "the little dog does",
          "a kind neighbour does",
          "the granddaughter does"
        ],
        "optionsZh": [
          "奶奶",
          "小狗",
          "善良的鄰居",
          "孫女"
        ],
        "correctIndex": 0,
        "explanationZh": "奶奶抓爺爺外套後面——所以是「Grandma does」,很簡單喔!",
        "sentenceZh": "爺爺拉蘿蔔,奶奶拉爺爺。",
        "tags": [
          "story",
          "ch20",
          "enormous-turnip"
        ],
        "subSkill": "detail"
      },
      {
        "type": "emoji-pick",
        "id": "kt-ch20-l3-x5",
        "level": "A2",
        "difficulty": "easy",
        "speaker": "narrator",
        "sentence": "Two people pull together but the turnip still does not come out.",
        "question": "How do they feel after that?",
        "options": [
          "🎉 happy and done",
          "😮 surprised and sad",
          "😄 proud and joyful",
          "😴 done and sleepy"
        ],
        "optionsZh": [
          "開心,完成了",
          "驚訝又難過",
          "驕傲又快樂",
          "睡著,累了"
        ],
        "correctIndex": 1,
        "explanationZh": "兩個人一起拉了,還是出不來——一定是「驚訝又難過」的心情呀!",
        "sentenceZh": "兩個人一起拉,蘿蔔還是沒出來。",
        "tags": [
          "story",
          "ch20",
          "enormous-turnip",
          "hook"
        ],
        "subSkill": "vocab"
      },
      {
        "type": "comprehension",
        "id": "kt-ch20-l3-x6",
        "level": "A2",
        "difficulty": "easy",
        "speaker": "narrator",
        "sentence": "They both pull. They count out loud. One, two, pull!",
        "question": "Why do they count out loud together?",
        "options": [
          "to frighten any nearby birds",
          "to teach the turnip some words",
          "so both pull at the exact moment",
          "so the neighbours can watch them"
        ],
        "optionsZh": [
          "嚇走附近的鳥",
          "教蘿蔔學說話",
          "讓兩人同時用力",
          "讓鄰居來觀看"
        ],
        "correctIndex": 2,
        "explanationZh": "一起數「One, two, pull!」就是要同時出力!",
        "sentenceZh": "他們一起拉。他們大聲數數。一、二、拉!",
        "tags": [
          "story",
          "ch20",
          "enormous-turnip",
          "teamwork"
        ],
        "subSkill": "inference"
      },
      {
        "type": "listen-tf",
        "id": "kt-ch20-l3-x7",
        "level": "A2",
        "difficulty": "medium",
        "speaker": "narrator",
        "sentence": "Two is not enough. Grandma looks at Grandpa and asks who else can help.",
        "questionEn": "Are Grandpa and Grandma going to stop trying now?",
        "options": [
          "Yes",
          "No"
        ],
        "correctIndex": 1,
        "explanationZh": "「who else can help?」——在問還有誰可以幫,說明他們不放棄,要繼續找幫手。答案是 No!",
        "sentenceZh": "兩個不夠。奶奶問爺爺:我們還能叫誰?",
        "tags": [
          "story",
          "ch20",
          "enormous-turnip",
          "inference"
        ]
      },
      {
        "type": "comprehension",
        "id": "kt-ch20-l3-x8",
        "level": "A2",
        "difficulty": "medium",
        "speaker": "narrator",
        "sentence": "One person tried and could not. Two together tried and still cannot.",
        "question": "What is the pattern in this story?",
        "options": [
          "rain falls every time they pull",
          "they give up after every turn",
          "the turnip gets smaller each try",
          "each time one more joins to try"
        ],
        "optionsZh": [
          "每次拉的時候下雨",
          "每次失敗後放棄",
          "每次蘿蔔變更小",
          "每次多一個加入"
        ],
        "correctIndex": 3,
        "explanationZh": "一個→兩個→還是不行……這就是「每次多一個人加入」的規律!這個故事就是這樣的結構。",
        "sentenceZh": "一個不行,兩個一起還是不行。",
        "tags": [
          "story",
          "ch20",
          "enormous-turnip"
        ],
        "subSkill": "gist"
      }
    ]
  },
  {
    "id": "kt-ch20-l4",
    "chapter": 20,
    "lessonInChapter": 4,
    "segmentType": "main-story",
    "storyId": "enormous-turnip",
    "storyBeat": "叫孫女來幫 — 越來越多人",
    "questions": [
      {
        "type": "tap-pairs",
        "id": "kt-ch20-l4-q1",
        "level": "A2",
        "difficulty": "easy",
        "speaker": "narrator",
        "sentence": "Here are 4 words you will meet in tonight's story.",
        "pairs": [
          {
            "left": "孫女",
            "right": "granddaughter"
          },
          {
            "left": "跑",
            "right": "run"
          },
          {
            "left": "圍裙",
            "right": "apron"
          },
          {
            "left": "一起",
            "right": "together"
          }
        ],
        "explanationZh": "本節新單字 (左中右英):\n🔑 granddaughter = 孫女\n🔑 run = 跑\n🔑 apron = 圍裙\n🔑 together = 一起\n背熟這 4 個字,故事就會輕鬆聽懂。",
        "tags": [
          "story",
          "ch20",
          "enormous-turnip",
          "vocab",
          "intro"
        ]
      },
      {
        "type": "narration",
        "id": "kt-ch20-l4-q2",
        "level": "A2",
        "difficulty": "easy",
        "speaker": "narrator",
        "sentence": "Grandma calls toward the house. \"Granddaughter, come help us!\"",
        "explanationZh": "奶奶對著屋子大叫:「孫女,快來幫我們!」",
        "tags": [
          "story",
          "ch20",
          "enormous-turnip"
        ]
      },
      {
        "type": "narration",
        "id": "kt-ch20-l4-q3",
        "level": "A2",
        "difficulty": "easy",
        "speaker": "narrator",
        "sentence": "A little girl runs out of the door. She is fast.",
        "explanationZh": "一個小女孩從門裡衝出來,跑得飛快。",
        "tags": [
          "story",
          "ch20",
          "enormous-turnip"
        ]
      },
      {
        "type": "listen-tf",
        "id": "kt-ch20-l4-q4",
        "level": "A2",
        "difficulty": "medium",
        "speaker": "narrator",
        "sentence": "She does not even put her shoes on. She runs to the garden.",
        "questionEn": "Is the granddaughter excited to help?",
        "options": [
          "Yes",
          "No"
        ],
        "correctIndex": 0,
        "explanationZh": "連鞋都沒穿就衝出去——這不是急著想幫忙是什麼?答案是 Yes!",
        "tags": [
          "story",
          "ch20",
          "enormous-turnip",
          "inference"
        ],
        "sentenceZh": "她連鞋子都沒穿就跑去園子了。"
      },
      {
        "type": "listen-mc",
        "id": "kt-ch20-l4-q5",
        "level": "A2",
        "difficulty": "easy",
        "speaker": "narrator",
        "sentence": "The little girl grabs the back of Grandma's apron with both hands.",
        "question": "What does Granddaughter hold on to?",
        "options": [
          "the lady in front of her",
          "the turnip's green leaves",
          "the open kitchen door",
          "her own two little shoes"
        ],
        "optionsZh": [
          "前面那位女士",
          "蘿蔔的綠葉子",
          "打開的廚房門",
          "她自己的小鞋子"
        ],
        "correctIndex": 0,
        "explanationZh": "抓的是奶奶的圍裙,也就是前面那位女士的衣服囉!",
        "tags": [
          "story",
          "ch20",
          "enormous-turnip"
        ],
        "subSkill": "detail",
        "sentenceZh": "小女孩用兩隻手抓住奶奶圍裙的後面。"
      },
      {
        "type": "narration",
        "id": "kt-ch20-l4-q6",
        "level": "A2",
        "difficulty": "easy",
        "speaker": "narrator",
        "sentence": "Grandpa pulls. Grandma pulls. Granddaughter pulls.",
        "explanationZh": "爺爺拉。奶奶拉。孫女拉。一個接著一個!",
        "tags": [
          "story",
          "ch20",
          "enormous-turnip"
        ]
      },
      {
        "type": "emoji-pick",
        "id": "kt-ch20-l4-q7",
        "level": "A2",
        "difficulty": "easy",
        "speaker": "narrator",
        "sentence": "How many people are pulling now?",
        "question": "How many?",
        "options": [
          "1️⃣ one",
          "3️⃣ three",
          "2️⃣ two",
          "4️⃣ four"
        ],
        "optionsZh": [
          "一個",
          "三個",
          "兩個",
          "四個"
        ],
        "correctIndex": 1,
        "explanationZh": "爺爺加奶奶加孫女——一加一加一等於三個人!",
        "tags": [
          "story",
          "ch20",
          "enormous-turnip",
          "hook"
        ],
        "subSkill": "vocab",
        "sentenceZh": "現在有幾個人在拉?"
      },
      {
        "type": "narration",
        "id": "kt-ch20-l4-q8",
        "level": "A2",
        "difficulty": "easy",
        "speaker": "narrator",
        "sentence": "Three of them pull at the same time. They count again.",
        "explanationZh": "三個人同時用力,嘴裡還一起數著。",
        "tags": [
          "story",
          "ch20",
          "enormous-turnip"
        ]
      },
      {
        "type": "listen-mc",
        "id": "kt-ch20-l4-q9",
        "level": "A2",
        "difficulty": "easy",
        "speaker": "narrator",
        "sentence": "Three pairs of hands. Three sets of feet pushing in the dirt.",
        "question": "What are they all doing together?",
        "options": [
          "walking back home",
          "eating a big dinner",
          "pulling as one team",
          "looking at the sky"
        ],
        "optionsZh": [
          "走路回家",
          "吃豐盛晚餐",
          "當一隊一起拉",
          "看天空"
        ],
        "correctIndex": 2,
        "explanationZh": "三雙手三雙腳全部一起使力——當然是當一隊一起拉啦!",
        "tags": [
          "story",
          "ch20",
          "enormous-turnip"
        ],
        "subSkill": "detail",
        "sentenceZh": "三雙手。三雙腳踩在土上用力。"
      },
      {
        "type": "comprehension",
        "id": "kt-ch20-l4-q10",
        "level": "A2",
        "difficulty": "medium",
        "speaker": "narrator",
        "sentence": "They pull and pull. The turnip will not move.",
        "question": "Why does the turnip still not move?",
        "options": [
          "the dirt is too soft",
          "Grandpa stopped pulling",
          "the leaves came off",
          "three is still not enough"
        ],
        "optionsZh": [
          "土太軟",
          "爺爺停了",
          "葉子掉了",
          "三個還是不夠"
        ],
        "correctIndex": 3,
        "explanationZh": "三個人全力拉了,蘿蔔還是沒動——代表三個還是不夠!",
        "tags": [
          "story",
          "ch20",
          "enormous-turnip"
        ],
        "subSkill": "inference",
        "sentenceZh": "他們一直拉,蘿蔔就是不動。"
      },
      {
        "type": "narration",
        "id": "kt-ch20-l4-q11",
        "level": "A2",
        "difficulty": "easy",
        "speaker": "narrator",
        "sentence": "Three is not enough either. Granddaughter looks around. \"We need more help!\"",
        "explanationZh": "三個還是不夠。孫女四處望:「我們還需要更多人!」",
        "tags": [
          "story",
          "ch20",
          "enormous-turnip"
        ]
      },
      {
        "type": "comprehension",
        "id": "kt-ch20-l4-x1",
        "level": "A2",
        "difficulty": "easy",
        "speaker": "narrator",
        "sentence": "The little girl runs out of the door without putting shoes on.",
        "question": "Why did she run without her shoes?",
        "options": [
          "too excited to wait",
          "she lost her shoes long ago",
          "shoes hurt her feet badly",
          "Grandma hid the shoes"
        ],
        "optionsZh": [
          "太興奮等不及",
          "她早就找不到鞋了",
          "鞋子傷她的腳",
          "奶奶把鞋藏起來了"
        ],
        "correctIndex": 0,
        "explanationZh": "連鞋都顧不上穿——就是「太興奮等不及」啦!這個小女孩真的很熱心。",
        "sentenceZh": "小女孩沒穿鞋就衝出門。",
        "tags": [
          "story",
          "ch20",
          "enormous-turnip"
        ],
        "subSkill": "inference"
      },
      {
        "type": "listen-tf",
        "id": "kt-ch20-l4-x2",
        "level": "A2",
        "difficulty": "medium",
        "speaker": "narrator",
        "sentence": "The little girl grabs the back of Grandma's apron with both hands.",
        "questionEn": "Does each helper hold the person just in front of them?",
        "options": [
          "Yes",
          "No"
        ],
        "correctIndex": 0,
        "explanationZh": "孫女抓奶奶、奶奶抓爺爺、爺爺抓蘿蔔——是的,每個人抓前面那個人。答案是 Yes!",
        "sentenceZh": "小女孩用兩隻手抓住奶奶圍裙的後面。",
        "tags": [
          "story",
          "ch20",
          "enormous-turnip",
          "inference"
        ]
      },
      {
        "type": "tap-pairs",
        "id": "kt-ch20-l4-x3",
        "level": "A2",
        "difficulty": "easy",
        "speaker": "narrator",
        "sentence": "Match the words from this lesson.",
        "pairs": [
          {
            "left": "跑",
            "right": "run"
          },
          {
            "left": "門",
            "right": "door"
          },
          {
            "left": "圍裙",
            "right": "apron"
          },
          {
            "left": "孫女",
            "right": "granddaughter"
          }
        ],
        "explanationZh": "🔑 run = 跑\n🔑 door = 門\n🔑 apron = 圍裙\n🔑 granddaughter = 孫女\n這節新單字,配對一下吧!",
        "tags": [
          "story",
          "ch20",
          "enormous-turnip",
          "vocab"
        ]
      },
      {
        "type": "comprehension",
        "id": "kt-ch20-l4-x4",
        "level": "A2",
        "difficulty": "easy",
        "speaker": "narrator",
        "sentence": "Grandpa pulls. Grandma pulls. Granddaughter pulls.",
        "question": "How many people are in the pulling line now?",
        "options": [
          "only Grandpa",
          "three people",
          "four helpers",
          "two siblings"
        ],
        "optionsZh": [
          "只有爺爺",
          "三個人",
          "四個幫手",
          "兩個兄弟姐妹"
        ],
        "correctIndex": 1,
        "explanationZh": "爺爺+奶奶+孫女 = 三個人!好整齊的一條線。",
        "sentenceZh": "爺爺拉,奶奶拉,孫女也拉。",
        "tags": [
          "story",
          "ch20",
          "enormous-turnip"
        ],
        "subSkill": "detail"
      },
      {
        "type": "emoji-pick",
        "id": "kt-ch20-l4-x5",
        "level": "A2",
        "difficulty": "easy",
        "speaker": "narrator",
        "sentence": "Three people pull together with all their strength.",
        "question": "What do they feel while pulling?",
        "options": [
          "😴 very sleepy",
          "😋 a bit hungry",
          "💪 strong and hopeful",
          "😱 very scared"
        ],
        "optionsZh": [
          "很想睡",
          "有點餓",
          "有力又有希望",
          "很害怕"
        ],
        "correctIndex": 2,
        "explanationZh": "三個人齊心拉——當然是「有力又有希望」的感覺!大家都相信這次可以!",
        "sentenceZh": "三個人一起用全力拉。",
        "tags": [
          "story",
          "ch20",
          "enormous-turnip",
          "hook"
        ],
        "subSkill": "vocab"
      },
      {
        "type": "comprehension",
        "id": "kt-ch20-l4-x6",
        "level": "A2",
        "difficulty": "medium",
        "speaker": "narrator",
        "sentence": "They pull and pull. The turnip will not move.",
        "question": "What does the family understand after three people fail?",
        "options": [
          "Grandpa should pull harder",
          "the turnip is rotten now",
          "they should dig around it",
          "they need even more help"
        ],
        "optionsZh": [
          "爺爺要更用力",
          "蘿蔔現在爛掉了",
          "應該在旁邊挖土",
          "他們需要更多幫忙"
        ],
        "correctIndex": 3,
        "explanationZh": "三個都不行了——那只有一個可能:「還需要更多幫忙」!",
        "sentenceZh": "他們一直拉,蘿蔔還是不動。",
        "tags": [
          "story",
          "ch20",
          "enormous-turnip"
        ],
        "subSkill": "inference"
      },
      {
        "type": "listen-tf",
        "id": "kt-ch20-l4-x7",
        "level": "A2",
        "difficulty": "medium",
        "speaker": "narrator",
        "sentence": "Three is not enough either. Granddaughter looks around for more help.",
        "questionEn": "Has the family given up on pulling the turnip?",
        "options": [
          "Yes",
          "No"
        ],
        "correctIndex": 1,
        "explanationZh": "孫女四處找更多幫手——沒有放棄,繼續找!答案是 No。",
        "sentenceZh": "三個還是不夠,孫女四處張望,找更多幫手。",
        "tags": [
          "story",
          "ch20",
          "enormous-turnip",
          "inference"
        ]
      },
      {
        "type": "comprehension",
        "id": "kt-ch20-l4-x8",
        "level": "A2",
        "difficulty": "easy",
        "speaker": "narrator",
        "sentence": "Each new person joins at the back of the line and holds the one in front.",
        "question": "Where does each new helper stand?",
        "options": [
          "at the end of the line",
          "at the front near the turnip",
          "off to the side alone",
          "on top of the others"
        ],
        "optionsZh": [
          "在隊伍最後面",
          "在靠近蘿蔔的前面",
          "在旁邊單獨站",
          "在別人上面"
        ],
        "correctIndex": 0,
        "explanationZh": "每個新幫手都接在最後面——這就是這個故事的規律:「在隊伍最後面」!",
        "sentenceZh": "每個新加入的人站在隊伍最後面,抓住前面的人。",
        "tags": [
          "story",
          "ch20",
          "enormous-turnip"
        ],
        "subSkill": "detail"
      }
    ]
  },
  {
    "id": "kt-ch20-l5",
    "chapter": 20,
    "lessonInChapter": 5,
    "segmentType": "main-story",
    "storyId": "enormous-turnip",
    "storyBeat": "叫小狗 — 還是不夠",
    "questions": [
      {
        "type": "tap-pairs",
        "id": "kt-ch20-l5-q1",
        "level": "A2",
        "difficulty": "easy",
        "speaker": "narrator",
        "sentence": "Here are 4 words you will meet in tonight's story.",
        "pairs": [
          {
            "left": "狗",
            "right": "dog"
          },
          {
            "left": "過來",
            "right": "over"
          },
          {
            "left": "牙齒",
            "right": "teeth"
          },
          {
            "left": "四個",
            "right": "four"
          }
        ],
        "explanationZh": "本節新單字 (左中右英):\n🔑 dog = 狗\n🔑 over = 過來\n🔑 teeth = 牙齒\n🔑 four = 四個\n背熟這 4 個字,故事就會輕鬆聽懂。",
        "tags": [
          "story",
          "ch20",
          "enormous-turnip",
          "vocab",
          "intro"
        ]
      },
      {
        "type": "narration",
        "id": "kt-ch20-l5-q2",
        "level": "A2",
        "difficulty": "easy",
        "speaker": "narrator",
        "sentence": "Granddaughter calls toward the yard. \"Little dog, come help us!\"",
        "explanationZh": "孫女對著院子叫:「小狗,快來幫我們!」",
        "tags": [
          "story",
          "ch20",
          "enormous-turnip"
        ]
      },
      {
        "type": "narration",
        "id": "kt-ch20-l5-q3",
        "level": "A2",
        "difficulty": "easy",
        "speaker": "narrator",
        "sentence": "The little dog runs over. His tail moves fast.",
        "explanationZh": "小狗聽到叫聲,立刻跑了過來,尾巴搖個不停。",
        "tags": [
          "story",
          "ch20",
          "enormous-turnip"
        ]
      },
      {
        "type": "listen-tf",
        "id": "kt-ch20-l5-q4",
        "level": "A2",
        "difficulty": "medium",
        "speaker": "narrator",
        "sentence": "The dog wags his tail. He looks up at the girl.",
        "questionEn": "Is the dog ready to help?",
        "options": [
          "Yes",
          "No"
        ],
        "correctIndex": 0,
        "explanationZh": "搖尾巴、抬頭看——這就是小狗說「我準備好了!」的方式。答案是 Yes!",
        "tags": [
          "story",
          "ch20",
          "enormous-turnip",
          "inference"
        ],
        "sentenceZh": "小狗搖著尾巴,抬頭看著小女孩。"
      },
      {
        "type": "listen-mc",
        "id": "kt-ch20-l5-q5",
        "level": "A2",
        "difficulty": "easy",
        "speaker": "narrator",
        "sentence": "The dog uses his teeth to hold the back of Granddaughter's dress.",
        "question": "How does the dog hold on?",
        "options": [
          "front paws on the ground",
          "mouth bites the dress",
          "ears flap in the wind",
          "tail wraps around her leg"
        ],
        "optionsZh": [
          "前腳踩在地上",
          "嘴巴咬住衣服",
          "耳朵在風裡飄",
          "尾巴繞她的腳"
        ],
        "correctIndex": 1,
        "explanationZh": "用牙齒咬住——也就是嘴巴咬住衣服,加入拉的隊伍!",
        "tags": [
          "story",
          "ch20",
          "enormous-turnip"
        ],
        "subSkill": "detail",
        "sentenceZh": "小狗用牙齒咬住孫女衣服的後面。"
      },
      {
        "type": "narration",
        "id": "kt-ch20-l5-q6",
        "level": "A2",
        "difficulty": "easy",
        "speaker": "narrator",
        "sentence": "Grandpa pulls. Grandma pulls. Granddaughter pulls. Dog pulls.",
        "explanationZh": "爺爺拉。奶奶拉。孫女拉。狗也拉。隊伍越來越長了!",
        "tags": [
          "story",
          "ch20",
          "enormous-turnip"
        ]
      },
      {
        "type": "emoji-pick",
        "id": "kt-ch20-l5-q7",
        "level": "A2",
        "difficulty": "easy",
        "speaker": "narrator",
        "sentence": "How many are pulling now?",
        "question": "How many?",
        "options": [
          "2️⃣ two",
          "3️⃣ three",
          "4️⃣ four",
          "5️⃣ five"
        ],
        "optionsZh": [
          "兩個",
          "三個",
          "四個",
          "五個"
        ],
        "correctIndex": 2,
        "explanationZh": "爺爺加奶奶加孫女加狗——數一數,四個!",
        "tags": [
          "story",
          "ch20",
          "enormous-turnip",
          "hook"
        ],
        "subSkill": "vocab",
        "sentenceZh": "現在有幾個在拉?"
      },
      {
        "type": "narration",
        "id": "kt-ch20-l5-q8",
        "level": "A2",
        "difficulty": "easy",
        "speaker": "narrator",
        "sentence": "Four of them pull. They count together. One, two, three, pull!",
        "explanationZh": "四個一起數:一、二、三——拉!",
        "tags": [
          "story",
          "ch20",
          "enormous-turnip"
        ]
      },
      {
        "type": "listen-mc",
        "id": "kt-ch20-l5-q9",
        "level": "A2",
        "difficulty": "easy",
        "speaker": "narrator",
        "sentence": "Even with the dog's teeth pulling too, the turnip stays put.",
        "question": "What happens with the dog helping?",
        "options": [
          "it pops right out",
          "the dog barks loudly",
          "the dog runs away",
          "it still does not budge"
        ],
        "optionsZh": [
          "馬上出來",
          "狗大聲叫",
          "狗跑掉",
          "還是沒動"
        ],
        "correctIndex": 3,
        "explanationZh": "狗加進來了,蘿蔔卻還是沒動——也就是,還是沒動。",
        "tags": [
          "story",
          "ch20",
          "enormous-turnip"
        ],
        "subSkill": "detail",
        "sentenceZh": "就算小狗的牙齒也一起拉,蘿蔔還是沒動。"
      },
      {
        "type": "comprehension",
        "id": "kt-ch20-l5-q10",
        "level": "A2",
        "difficulty": "medium",
        "speaker": "narrator",
        "sentence": "A dog joins the family. Even four pulling, the turnip stays.",
        "question": "What is this scene mainly showing?",
        "options": [
          "more help joins but it is still not enough",
          "the dog wins a running race in the field",
          "the family sits down to eat a big dinner",
          "a clever dog learns a brand new trick"
        ],
        "optionsZh": [
          "又多了幫手但還是不夠",
          "狗在田裡贏了一場賽跑",
          "全家坐下來吃一頓大餐",
          "聰明的狗學會一個全新的把戲"
        ],
        "correctIndex": 0,
        "explanationZh": "四個幫手齊力拉,蘿蔔依舊紋絲不動——這一幕的重點是:幫手越來越多,但還是不夠!",
        "tags": [
          "story",
          "ch20",
          "enormous-turnip",
          "gist"
        ],
        "subSkill": "gist",
        "sentenceZh": "家裡的狗加入了。就算四個一起拉,蘿蔔還是沒動。"
      },
      {
        "type": "narration",
        "id": "kt-ch20-l5-q11",
        "level": "A2",
        "difficulty": "easy",
        "speaker": "narrator",
        "sentence": "Four is not enough. The dog barks once. \"Maybe my friend the cat can come...\"",
        "explanationZh": "四個還是不夠。小狗叫了一聲:「也許我的好朋友貓咪可以來……」",
        "tags": [
          "story",
          "ch20",
          "enormous-turnip"
        ]
      },
      {
        "type": "comprehension",
        "id": "kt-ch20-l5-x1",
        "level": "A2",
        "difficulty": "easy",
        "speaker": "narrator",
        "sentence": "The little dog runs over. His tail moves fast.",
        "question": "What does a fast-moving tail usually tell us about a dog?",
        "options": [
          "strong hunger right now",
          "joy and eagerness",
          "pain or sickness today",
          "chasing something nearby"
        ],
        "optionsZh": [
          "強烈的飢餓感",
          "開心和熱情",
          "疼痛或生病",
          "正在追什麼"
        ],
        "correctIndex": 1,
        "explanationZh": "尾巴搖快 = 高興!「joy and eagerness」最貼切。",
        "sentenceZh": "小狗跑過來,牠的尾巴搖得好快。",
        "tags": [
          "story",
          "ch20",
          "enormous-turnip",
          "character"
        ],
        "subSkill": "inference"
      },
      {
        "type": "listen-tf",
        "id": "kt-ch20-l5-x2",
        "level": "A2",
        "difficulty": "medium",
        "speaker": "narrator",
        "sentence": "The dog uses his teeth to hold the back of Granddaughter's dress.",
        "questionEn": "Does the dog grab onto the turnip directly?",
        "options": [
          "Yes",
          "No"
        ],
        "correctIndex": 1,
        "explanationZh": "小狗咬的是孫女的衣服,不是蘿蔔——所以答案是 No,他抓的是前面的人!",
        "sentenceZh": "小狗用牙齒咬住孫女衣服的後面。",
        "tags": [
          "story",
          "ch20",
          "enormous-turnip",
          "inference"
        ]
      },
      {
        "type": "tap-pairs",
        "id": "kt-ch20-l5-x3",
        "level": "A2",
        "difficulty": "easy",
        "speaker": "narrator",
        "sentence": "Match the words from this lesson.",
        "pairs": [
          {
            "left": "狗",
            "right": "dog"
          },
          {
            "left": "牙齒",
            "right": "teeth"
          },
          {
            "left": "尾巴",
            "right": "tail"
          },
          {
            "left": "衣服",
            "right": "dress"
          }
        ],
        "explanationZh": "🔑 dog = 狗\n🔑 teeth = 牙齒\n🔑 tail = 尾巴\n🔑 dress = 衣服\n這節小狗登場的單字!",
        "tags": [
          "story",
          "ch20",
          "enormous-turnip",
          "vocab"
        ]
      },
      {
        "type": "comprehension",
        "id": "kt-ch20-l5-x4",
        "level": "A2",
        "difficulty": "easy",
        "speaker": "narrator",
        "sentence": "Four of them pull. They count together. One, two, three, pull!",
        "question": "Who is pulling this time?",
        "options": [
          "the dog and the cat alone",
          "only Grandpa and the dog",
          "Grandpa, Grandma, the girl, the dog",
          "Grandma, the dog, a mouse"
        ],
        "optionsZh": [
          "只有狗和貓",
          "只有爺爺和狗",
          "爺爺奶奶孫女狗",
          "奶奶狗和老鼠"
        ],
        "correctIndex": 2,
        "explanationZh": "爺爺+奶奶+孫女+狗=四個!「Grandpa, Grandma, the girl, the dog」全部都有。",
        "sentenceZh": "四個一起拉,大聲數:一、二、三——拉!",
        "tags": [
          "story",
          "ch20",
          "enormous-turnip"
        ],
        "subSkill": "detail"
      },
      {
        "type": "emoji-pick",
        "id": "kt-ch20-l5-x5",
        "level": "A2",
        "difficulty": "easy",
        "speaker": "narrator",
        "sentence": "Even with the dog's teeth pulling, the turnip stays in the ground.",
        "question": "Which emoji best shows what the turnip does?",
        "options": [
          "🌱 sprouts up",
          "💧 melts down",
          "✈️ flies away",
          "🪨 stays put"
        ],
        "optionsZh": [
          "向上冒出",
          "融化",
          "飛走",
          "紋絲不動"
        ],
        "correctIndex": 3,
        "explanationZh": "「stays in the ground」= 紋絲不動——選「🪨 stays put」!",
        "sentenceZh": "即使小狗咬住用力拉,蘿蔔還是留在地裡。",
        "tags": [
          "story",
          "ch20",
          "enormous-turnip",
          "conflict"
        ],
        "subSkill": "detail"
      },
      {
        "type": "comprehension",
        "id": "kt-ch20-l5-x6",
        "level": "A2",
        "difficulty": "medium",
        "speaker": "narrator",
        "sentence": "The dog barks once. Maybe his friend the cat can help.",
        "question": "Why does the dog think of the cat?",
        "options": [
          "he wants one more helper",
          "cats are bigger than dogs",
          "the cat has sharp claws",
          "he is bored of the dog"
        ],
        "optionsZh": [
          "他要多一個幫手",
          "貓比狗大",
          "貓有尖爪子",
          "他對狗膩了"
        ],
        "correctIndex": 0,
        "explanationZh": "四個還是不夠——所以「他要多一個幫手」!小狗想到了朋友貓咪。",
        "sentenceZh": "小狗叫了一聲。也許他朋友貓咪可以來幫忙。",
        "tags": [
          "story",
          "ch20",
          "enormous-turnip"
        ],
        "subSkill": "inference"
      },
      {
        "type": "listen-tf",
        "id": "kt-ch20-l5-x7",
        "level": "A2",
        "difficulty": "medium",
        "speaker": "narrator",
        "sentence": "Four is not enough. The dog barks once and looks toward the wall.",
        "questionEn": "Is the dog asking someone new for help?",
        "options": [
          "Yes",
          "No"
        ],
        "correctIndex": 0,
        "explanationZh": "叫一聲、望向牆邊——當然是在叫新幫手貓咪。答案是 Yes!",
        "sentenceZh": "四個不夠。小狗叫了一聲,看向牆那邊。",
        "tags": [
          "story",
          "ch20",
          "enormous-turnip",
          "inference"
        ]
      },
      {
        "type": "comprehension",
        "id": "kt-ch20-l5-x8",
        "level": "A2",
        "difficulty": "easy",
        "speaker": "narrator",
        "sentence": "A dog joins the family. Even four pulling, the turnip stays.",
        "question": "What lesson is this scene building up to?",
        "options": [
          "dogs are the best helpers",
          "every single helper counts",
          "only people can pull things",
          "turnips are bad to eat"
        ],
        "optionsZh": [
          "狗是最好的幫手",
          "每個幫手都很重要",
          "只有人才能拉東西",
          "蘿蔔不好吃"
        ],
        "correctIndex": 1,
        "explanationZh": "一個又一個加進來——故事在告訴我們「每個幫手都很重要」,缺一不可!",
        "sentenceZh": "小狗加入了。就算四個一起拉,蘿蔔還是沒動。",
        "tags": [
          "story",
          "ch20",
          "enormous-turnip"
        ],
        "subSkill": "gist"
      }
    ]
  },
  {
    "id": "kt-ch20-l6",
    "chapter": 20,
    "lessonInChapter": 6,
    "segmentType": "main-story",
    "storyId": "enormous-turnip",
    "storyBeat": "叫小貓 — 還是不行",
    "questions": [
      {
        "type": "tap-pairs",
        "id": "kt-ch20-l6-q1",
        "level": "A2",
        "difficulty": "easy",
        "speaker": "narrator",
        "sentence": "Here are 4 words you will meet in tonight's story.",
        "pairs": [
          {
            "left": "貓",
            "right": "cat"
          },
          {
            "left": "走",
            "right": "walk"
          },
          {
            "left": "尾巴",
            "right": "tail"
          },
          {
            "left": "足夠",
            "right": "enough"
          }
        ],
        "explanationZh": "本節新單字 (左中右英):\n🔑 cat = 貓\n🔑 walk = 走\n🔑 tail = 尾巴\n🔑 enough = 足夠\n背熟這 4 個字,故事就會輕鬆聽懂。",
        "tags": [
          "story",
          "ch20",
          "enormous-turnip",
          "vocab",
          "intro"
        ]
      },
      {
        "type": "narration",
        "id": "kt-ch20-l6-q2",
        "level": "A2",
        "difficulty": "easy",
        "speaker": "narrator",
        "sentence": "The dog calls toward the wall. \"Cat, come help us!\"",
        "explanationZh": "小狗對著牆那邊叫:「貓咪,快來幫我們!」",
        "tags": [
          "story",
          "ch20",
          "enormous-turnip"
        ]
      },
      {
        "type": "narration",
        "id": "kt-ch20-l6-q3",
        "level": "A2",
        "difficulty": "easy",
        "speaker": "narrator",
        "sentence": "The cat walks over slowly. She takes her time.",
        "explanationZh": "貓咪慢慢地踱過來。她不急——貓咪本來就這樣嘛。",
        "tags": [
          "story",
          "ch20",
          "enormous-turnip"
        ]
      },
      {
        "type": "listen-tf",
        "id": "kt-ch20-l6-q4",
        "level": "A2",
        "difficulty": "medium",
        "speaker": "narrator",
        "sentence": "The cat does not run. She stops to look at the turnip first.",
        "questionEn": "Does the cat care about being fast?",
        "options": [
          "Yes",
          "No"
        ],
        "correctIndex": 1,
        "explanationZh": "慢慢走、還先看一看——貓咪根本不在乎快不快。答案是 No。",
        "tags": [
          "story",
          "ch20",
          "enormous-turnip",
          "inference"
        ],
        "sentenceZh": "貓咪沒有跑。她先停下來看了看蘿蔔。"
      },
      {
        "type": "listen-mc",
        "id": "kt-ch20-l6-q5",
        "level": "A2",
        "difficulty": "easy",
        "speaker": "narrator",
        "sentence": "The cat holds the dog's tail gently between her front paws.",
        "question": "How does the cat hold on?",
        "options": [
          "with her teeth on a leaf",
          "on Granddaughter's shoe",
          "with paws on the dog's tail",
          "around Grandpa's leg"
        ],
        "optionsZh": [
          "用牙齒咬葉子",
          "抓孫女的鞋",
          "前腳抱狗的尾巴",
          "抱爺爺的腳"
        ],
        "correctIndex": 2,
        "explanationZh": "用前腳抱住狗的尾巴——加入隊伍的方式真有貓咪風格!",
        "tags": [
          "story",
          "ch20",
          "enormous-turnip"
        ],
        "subSkill": "detail",
        "sentenceZh": "貓咪用前腳輕輕地抱住狗的尾巴。"
      },
      {
        "type": "narration",
        "id": "kt-ch20-l6-q6",
        "level": "A2",
        "difficulty": "easy",
        "speaker": "narrator",
        "sentence": "Five of them pull now. Everyone pulls as hard as they can.",
        "explanationZh": "現在五個人一起拉了。每個都使出全力。",
        "tags": [
          "story",
          "ch20",
          "enormous-turnip"
        ]
      },
      {
        "type": "emoji-pick",
        "id": "kt-ch20-l6-q7",
        "level": "A2",
        "difficulty": "easy",
        "speaker": "narrator",
        "sentence": "How many are pulling now?",
        "question": "How many?",
        "options": [
          "3️⃣ three",
          "4️⃣ four",
          "6️⃣ six",
          "5️⃣ five"
        ],
        "optionsZh": [
          "三個",
          "四個",
          "六個",
          "五個"
        ],
        "correctIndex": 3,
        "explanationZh": "爺爺加奶奶加孫女加狗加貓——五個!",
        "tags": [
          "story",
          "ch20",
          "enormous-turnip",
          "hook"
        ],
        "subSkill": "vocab",
        "sentenceZh": "現在有幾個在拉?"
      },
      {
        "type": "narration",
        "id": "kt-ch20-l6-q8",
        "level": "A2",
        "difficulty": "easy",
        "speaker": "narrator",
        "sentence": "They count again. One, two, three, pull!",
        "explanationZh": "大家又數一次:一、二、三——拉!",
        "tags": [
          "story",
          "ch20",
          "enormous-turnip"
        ]
      },
      {
        "type": "listen-mc",
        "id": "kt-ch20-l6-q9",
        "level": "A2",
        "difficulty": "easy",
        "speaker": "narrator",
        "sentence": "The turnip moves a tiny bit. The top wobbles in the dirt.",
        "question": "What is different this time?",
        "options": [
          "the turnip moves a little",
          "the turnip flies up",
          "the dirt turns to mud",
          "a new green leaf grows out"
        ],
        "optionsZh": [
          "蘿蔔動了一點",
          "蘿蔔飛起來",
          "土變泥",
          "長出新的綠葉"
        ],
        "correctIndex": 0,
        "explanationZh": "這次不一樣了——蘿蔔動了一點點!雖然還沒出來,但有進展喔。",
        "tags": [
          "story",
          "ch20",
          "enormous-turnip"
        ],
        "subSkill": "detail",
        "sentenceZh": "蘿蔔動了一點點。頂端在土裡搖了一下。"
      },
      {
        "type": "comprehension",
        "id": "kt-ch20-l6-q10",
        "level": "A2",
        "difficulty": "medium",
        "speaker": "narrator",
        "sentence": "But after that tiny move, the turnip stops. It is still stuck.",
        "question": "Why did the turnip move only a little?",
        "options": [
          "the cat is too small to help",
          "almost enough, but one more is needed",
          "the dirt around it is much too soft",
          "they are pulling the wrong way"
        ],
        "optionsZh": [
          "貓太小幫不到",
          "快夠了 + 還差一個",
          "周圍的土太軟了",
          "拉錯方向"
        ],
        "correctIndex": 1,
        "explanationZh": "動了一下又停——就差那麼一點,還需要再多一個幫手!",
        "tags": [
          "story",
          "ch20",
          "enormous-turnip"
        ],
        "subSkill": "inference",
        "sentenceZh": "但動了那麼一點之後,蘿蔔又停了。還是卡著。"
      },
      {
        "type": "narration",
        "id": "kt-ch20-l6-q11",
        "level": "A2",
        "difficulty": "easy",
        "speaker": "narrator",
        "sentence": "It moved! But not enough. The cat looks at her little friend by the wall...",
        "explanationZh": "動了!但還不夠。貓咪看向牆邊的那位小朋友……",
        "tags": [
          "story",
          "ch20",
          "enormous-turnip"
        ]
      },
      {
        "type": "comprehension",
        "id": "kt-ch20-l6-x1",
        "level": "A2",
        "difficulty": "easy",
        "speaker": "narrator",
        "sentence": "The cat walks over slowly. She takes her time.",
        "question": "How does the cat arrive?",
        "options": [
          "scared and hiding",
          "fast and barking",
          "slow and relaxed",
          "loud and bouncy"
        ],
        "optionsZh": [
          "躲起來害怕",
          "又快又叫",
          "慢慢悠悠",
          "吵吵鬧鬧"
        ],
        "correctIndex": 2,
        "explanationZh": "「walks slowly + takes her time」——慢慢走、不急不忙,就是「慢慢悠悠」的貓咪風格!",
        "sentenceZh": "貓咪慢慢踱過來,她不慌不忙。",
        "tags": [
          "story",
          "ch20",
          "enormous-turnip"
        ],
        "subSkill": "detail"
      },
      {
        "type": "listen-tf",
        "id": "kt-ch20-l6-x2",
        "level": "A2",
        "difficulty": "medium",
        "speaker": "narrator",
        "sentence": "The cat stops to look at the turnip first before joining the line.",
        "questionEn": "Does the cat rush straight to help without looking?",
        "options": [
          "Yes",
          "No"
        ],
        "correctIndex": 1,
        "explanationZh": "她先停下來看一看——沒有直衝過去。答案是 No,貓咪有自己的節奏!",
        "sentenceZh": "貓咪先停下來看了看蘿蔔,才加入隊伍。",
        "tags": [
          "story",
          "ch20",
          "enormous-turnip",
          "inference"
        ]
      },
      {
        "type": "tap-pairs",
        "id": "kt-ch20-l6-x3",
        "level": "A2",
        "difficulty": "easy",
        "speaker": "narrator",
        "sentence": "Match the words from this lesson.",
        "pairs": [
          {
            "left": "貓",
            "right": "cat"
          },
          {
            "left": "前腳",
            "right": "paws"
          },
          {
            "left": "慢慢",
            "right": "slowly"
          },
          {
            "left": "五個",
            "right": "five"
          }
        ],
        "explanationZh": "🔑 cat = 貓\n🔑 paws = 前腳\n🔑 slowly = 慢慢\n🔑 five = 五個\n貓咪登場的重點字!",
        "tags": [
          "story",
          "ch20",
          "enormous-turnip",
          "vocab"
        ]
      },
      {
        "type": "comprehension",
        "id": "kt-ch20-l6-x4",
        "level": "A2",
        "difficulty": "easy",
        "speaker": "narrator",
        "sentence": "The cat holds the dog's tail gently between her front paws.",
        "question": "Which part of the cat's body grips the dog's tail?",
        "options": [
          "a piece of rope",
          "her sharp teeth",
          "her hind legs",
          "her two forepaws"
        ],
        "optionsZh": [
          "一條繩子",
          "她的尖牙",
          "她的後腿",
          "她的兩隻前爪"
        ],
        "correctIndex": 3,
        "explanationZh": "「front paws」就是前爪——「forepaws」是同義詞,選 A!",
        "sentenceZh": "貓咪輕輕地用前爪夾住小狗的尾巴。",
        "tags": [
          "story",
          "ch20",
          "enormous-turnip",
          "detail"
        ],
        "subSkill": "detail"
      },
      {
        "type": "emoji-pick",
        "id": "kt-ch20-l6-x5",
        "level": "A2",
        "difficulty": "easy",
        "speaker": "narrator",
        "sentence": "Five are all pulling together now, but the turnip only moves a tiny bit.",
        "question": "How close are they to getting it out?",
        "options": [
          "🎯 very close now",
          "🚫 nowhere near it",
          "✅ already done",
          "😴 they stopped trying"
        ],
        "optionsZh": [
          "非常接近了",
          "還差很遠",
          "已經完成了",
          "他們停下來了"
        ],
        "correctIndex": 0,
        "explanationZh": "「moves a tiny bit」——動了一點點!就差那麼一步,說明「非常接近了」!",
        "sentenceZh": "五個一起拉,蘿蔔動了一點點。",
        "tags": [
          "story",
          "ch20",
          "enormous-turnip",
          "hook"
        ],
        "subSkill": "vocab"
      },
      {
        "type": "comprehension",
        "id": "kt-ch20-l6-x6",
        "level": "A2",
        "difficulty": "medium",
        "speaker": "narrator",
        "sentence": "The turnip moved a tiny bit but stopped again. It is still stuck.",
        "question": "What does this small move mean for the family?",
        "options": [
          "the turnip is broken inside",
          "hope—just one more is needed",
          "they are pulling the wrong way",
          "the problem is now too big"
        ],
        "optionsZh": [
          "蘿蔔裡面壞了",
          "有希望,還差一個人",
          "他們拉錯方向了",
          "問題現在太大了"
        ],
        "correctIndex": 1,
        "explanationZh": "動了一點點代表快要了!所以是「有希望,還差一個人」——多加一個就成功!",
        "sentenceZh": "蘿蔔動了一點點,但又停了。還是卡著。",
        "tags": [
          "story",
          "ch20",
          "enormous-turnip"
        ],
        "subSkill": "inference"
      },
      {
        "type": "listen-tf",
        "id": "kt-ch20-l6-x7",
        "level": "A2",
        "difficulty": "medium",
        "speaker": "narrator",
        "sentence": "The cat looks at her little friend by the wall.",
        "questionEn": "Is there one more helper nearby who has not joined yet?",
        "options": [
          "Yes",
          "No"
        ],
        "correctIndex": 0,
        "explanationZh": "牆邊還有一個小朋友——就是小老鼠!還沒加入的幫手確實存在。答案是 Yes!",
        "sentenceZh": "貓咪看向牆邊的小朋友。",
        "tags": [
          "story",
          "ch20",
          "enormous-turnip",
          "inference"
        ]
      },
      {
        "type": "comprehension",
        "id": "kt-ch20-l6-x8",
        "level": "A2",
        "difficulty": "easy",
        "speaker": "narrator",
        "sentence": "Five of them pull now. Everyone pulls as hard as they can.",
        "question": "Who is the fifth helper to join?",
        "options": [
          "a bird",
          "the dog",
          "the cat",
          "the mouse"
        ],
        "optionsZh": [
          "一隻鳥",
          "狗",
          "貓咪",
          "老鼠"
        ],
        "correctIndex": 2,
        "explanationZh": "爺爺、奶奶、孫女、狗——第五個是貓咪!「the cat」就是第五位!",
        "sentenceZh": "現在五個一起拉,每個都使出全力。",
        "tags": [
          "story",
          "ch20",
          "enormous-turnip"
        ],
        "subSkill": "detail"
      }
    ]
  },
  {
    "id": "kt-ch20-l7",
    "chapter": 20,
    "lessonInChapter": 7,
    "segmentType": "main-story",
    "storyId": "enormous-turnip",
    "storyBeat": "叫小老鼠 — 終於拔出來!全家分享",
    "questions": [
      {
        "type": "tap-pairs",
        "id": "kt-ch20-l7-q1",
        "level": "A2",
        "difficulty": "easy",
        "speaker": "narrator",
        "sentence": "Here are 4 words you will meet in tonight's story.",
        "pairs": [
          {
            "left": "老鼠",
            "right": "mouse"
          },
          {
            "left": "六個",
            "right": "six"
          },
          {
            "left": "出來",
            "right": "out"
          },
          {
            "left": "分享",
            "right": "share"
          }
        ],
        "explanationZh": "本節新單字 (左中右英):\n🔑 mouse = 老鼠\n🔑 six = 六個\n🔑 out = 出來\n🔑 share = 分享\n背熟這 4 個字,故事就會輕鬆聽懂。",
        "tags": [
          "story",
          "ch20",
          "enormous-turnip",
          "vocab",
          "intro"
        ]
      },
      {
        "type": "narration",
        "id": "kt-ch20-l7-q2",
        "level": "A2",
        "difficulty": "easy",
        "speaker": "narrator",
        "sentence": "The cat calls toward the small hole. \"Little mouse, come help us!\"",
        "explanationZh": "貓咪對著小洞叫:「小老鼠,快來幫我們!」",
        "tags": [
          "story",
          "ch20",
          "enormous-turnip"
        ]
      },
      {
        "type": "narration",
        "id": "kt-ch20-l7-q3",
        "level": "A2",
        "difficulty": "easy",
        "speaker": "narrator",
        "sentence": "A little mouse runs out. She is the smallest of all.",
        "explanationZh": "一隻小小的老鼠跑出來了。她是所有人裡面最小的一個。",
        "tags": [
          "story",
          "ch20",
          "enormous-turnip"
        ]
      },
      {
        "type": "listen-tf",
        "id": "kt-ch20-l7-q4",
        "level": "A2",
        "difficulty": "medium",
        "speaker": "narrator",
        "sentence": "The mouse is tiny. But she does not say she is too small.",
        "questionEn": "Does the mouse think size matters here?",
        "options": [
          "Yes",
          "No"
        ],
        "correctIndex": 1,
        "explanationZh": "小小的她,一句「我太小了」都沒說——她完全不把身材當回事嘛!答案是 No。",
        "tags": [
          "story",
          "ch20",
          "enormous-turnip",
          "inference"
        ],
        "sentenceZh": "老鼠很小。但她沒有說自己太小幫不上忙。"
      },
      {
        "type": "listen-mc",
        "id": "kt-ch20-l7-q5",
        "level": "A2",
        "difficulty": "easy",
        "speaker": "narrator",
        "sentence": "The little mouse holds on to the cat's tail with both paws.",
        "question": "How does the mouse hold on?",
        "options": [
          "holds the dog by an ear",
          "sits on Grandpa's boot",
          "pulls a turnip leaf",
          "grabs the furry one's tail"
        ],
        "optionsZh": [
          "抓狗的耳朵",
          "坐在爺爺靴子上",
          "扯蘿蔔葉子",
          "抓住毛毛那隻的尾巴"
        ],
        "correctIndex": 3,
        "explanationZh": "抱住貓咪的尾巴——貓咪是毛毛的那隻,所以是抓住毛毛那隻的尾巴!",
        "tags": [
          "story",
          "ch20",
          "enormous-turnip"
        ],
        "subSkill": "detail",
        "sentenceZh": "小老鼠用兩隻小爪子抱住貓咪的尾巴。"
      },
      {
        "type": "narration",
        "id": "kt-ch20-l7-q6",
        "level": "A2",
        "difficulty": "easy",
        "speaker": "narrator",
        "sentence": "Six of them pull now. The smallest one is at the end.",
        "explanationZh": "六個一起拉了!最小的老鼠排在最後面。",
        "tags": [
          "story",
          "ch20",
          "enormous-turnip"
        ]
      },
      {
        "type": "emoji-pick",
        "id": "kt-ch20-l7-q7",
        "level": "A2",
        "difficulty": "easy",
        "speaker": "narrator",
        "sentence": "How many are pulling at the end?",
        "question": "How many?",
        "options": [
          "6️⃣ six",
          "5️⃣ five",
          "4️⃣ four",
          "7️⃣ seven"
        ],
        "optionsZh": [
          "六個",
          "五個",
          "四個",
          "七個"
        ],
        "correctIndex": 0,
        "explanationZh": "爺爺加奶奶加孫女加狗加貓加老鼠——一起數,六個!",
        "tags": [
          "story",
          "ch20",
          "enormous-turnip",
          "hook"
        ],
        "subSkill": "vocab",
        "sentenceZh": "最後有幾個在拉?"
      },
      {
        "type": "narration",
        "id": "kt-ch20-l7-q8",
        "level": "A2",
        "difficulty": "easy",
        "speaker": "narrator",
        "sentence": "They count one more time. One, two, three, pull!",
        "explanationZh": "大家最後再數一次:一、二、三——拉!",
        "tags": [
          "story",
          "ch20",
          "enormous-turnip"
        ]
      },
      {
        "type": "listen-mc",
        "id": "kt-ch20-l7-q9",
        "level": "A2",
        "difficulty": "easy",
        "speaker": "narrator",
        "sentence": "Out comes the turnip! Everyone falls over backward in a happy pile.",
        "question": "What happens this time?",
        "options": [
          "the turnip stays stuck",
          "the turnip pops out",
          "the rope breaks",
          "a storm comes"
        ],
        "optionsZh": [
          "還是卡住",
          "蘿蔔出來了",
          "繩子斷了",
          "暴風雨來了"
        ],
        "correctIndex": 1,
        "explanationZh": "這次蘿蔔出來了!大家開心到一起往後倒。",
        "tags": [
          "story",
          "ch20",
          "enormous-turnip"
        ],
        "subSkill": "detail",
        "sentenceZh": "蘿蔔出來了!大家開心地一起倒在地上。"
      },
      {
        "type": "comprehension",
        "id": "kt-ch20-l7-q10",
        "level": "A2",
        "difficulty": "medium",
        "speaker": "narrator",
        "sentence": "The smallest mouse was the last help. That tiny push was the one.",
        "question": "What does this story teach us?",
        "options": [
          "only big strong helpers count",
          "working alone is always fastest",
          "even the smallest helper matters",
          "turnips grow only in summer"
        ],
        "optionsZh": [
          "只有又大又壯的幫手有用",
          "一個人做最快",
          "再小的幫忙都重要",
          "蘿蔔只夏天長"
        ],
        "correctIndex": 2,
        "explanationZh": "最小的老鼠是最後那一推——故事想告訴我們:再小的幫忙都重要,少了誰都不行!",
        "tags": [
          "story",
          "ch20",
          "enormous-turnip"
        ],
        "subSkill": "inference",
        "sentenceZh": "最小的老鼠是最後加入的那個。就差她那一點點力氣。"
      },
      {
        "type": "narration",
        "id": "kt-ch20-l7-q11",
        "level": "A2",
        "difficulty": "easy",
        "speaker": "narrator",
        "sentence": "The whole family shares a big turnip dinner. Even the mouse gets a seat at the table...",
        "explanationZh": "全家一起吃大蘿蔔晚餐,連小老鼠都有一個位子坐……",
        "tags": [
          "story",
          "ch20",
          "enormous-turnip"
        ]
      },
      {
        "type": "comprehension",
        "id": "kt-ch20-l7-x1",
        "level": "A2",
        "difficulty": "easy",
        "speaker": "narrator",
        "sentence": "A little mouse runs out. She is the smallest of all.",
        "question": "How does the mouse compare to all the others?",
        "options": [
          "faster than every animal",
          "older than anyone else",
          "louder than the dog today",
          "she is the smallest helper"
        ],
        "optionsZh": [
          "比所有動物都快",
          "比任何人都年長",
          "今天比小狗聲音大",
          "她是最小的幫手"
        ],
        "correctIndex": 3,
        "explanationZh": "「She is the smallest of all」——mouse 是所有幫手中最小的!",
        "sentenceZh": "一隻小老鼠跑出來了,牠是所有人中最小的。",
        "tags": [
          "story",
          "ch20",
          "enormous-turnip",
          "character"
        ],
        "subSkill": "detail"
      },
      {
        "type": "listen-tf",
        "id": "kt-ch20-l7-x2",
        "level": "A2",
        "difficulty": "medium",
        "speaker": "narrator",
        "sentence": "The mouse is tiny. But she does not say she is too small.",
        "questionEn": "Does the mouse let her small size stop her from helping?",
        "options": [
          "Yes",
          "No"
        ],
        "correctIndex": 1,
        "explanationZh": "她沒說「我太小了」——根本沒讓身材擋住她。答案是 No,小老鼠好勇敢!",
        "sentenceZh": "老鼠很小,但她沒說自己太小幫不上忙。",
        "tags": [
          "story",
          "ch20",
          "enormous-turnip",
          "inference"
        ]
      },
      {
        "type": "tap-pairs",
        "id": "kt-ch20-l7-x3",
        "level": "A2",
        "difficulty": "easy",
        "speaker": "narrator",
        "sentence": "Match the words from this lesson.",
        "pairs": [
          {
            "left": "老鼠",
            "right": "mouse"
          },
          {
            "left": "爪子",
            "right": "paws"
          },
          {
            "left": "出來",
            "right": "out"
          },
          {
            "left": "分享",
            "right": "share"
          }
        ],
        "explanationZh": "🔑 mouse = 老鼠\n🔑 paws = 爪子\n🔑 out = 出來\n🔑 share = 分享\n結局篇的關鍵字!",
        "tags": [
          "story",
          "ch20",
          "enormous-turnip",
          "vocab"
        ]
      },
      {
        "type": "comprehension",
        "id": "kt-ch20-l7-x4",
        "level": "A2",
        "difficulty": "easy",
        "speaker": "narrator",
        "sentence": "Six of them pull now. The smallest one is at the end.",
        "question": "Where does the mouse stand?",
        "options": [
          "last in the line",
          "right behind Grandpa",
          "in front of the cat",
          "next to Grandma"
        ],
        "optionsZh": [
          "隊伍最後面",
          "爺爺後面",
          "貓前面",
          "奶奶旁邊"
        ],
        "correctIndex": 0,
        "explanationZh": "「smallest at the end」——最小的在最後面!老鼠排在隊伍末尾。",
        "sentenceZh": "六個一起拉,最小的那個在最後面。",
        "tags": [
          "story",
          "ch20",
          "enormous-turnip"
        ],
        "subSkill": "detail"
      },
      {
        "type": "emoji-pick",
        "id": "kt-ch20-l7-x5",
        "level": "A2",
        "difficulty": "easy",
        "speaker": "narrator",
        "sentence": "Out comes the turnip! Everyone falls over in a happy pile.",
        "question": "How does everyone feel at the end?",
        "options": [
          "😢 sad and sorry",
          "🎊 happy and joyful",
          "😠 angry at someone",
          "😴 too tired to care"
        ],
        "optionsZh": [
          "難過後悔",
          "開心愉快",
          "對某人生氣",
          "太累不在乎"
        ],
        "correctIndex": 1,
        "explanationZh": "「everyone falls over in a happy pile」——大家開心地倒成一堆!答案是「開心愉快」!",
        "sentenceZh": "蘿蔔出來了!大家開心地一起往後倒。",
        "tags": [
          "story",
          "ch20",
          "enormous-turnip",
          "hook"
        ],
        "subSkill": "vocab"
      },
      {
        "type": "comprehension",
        "id": "kt-ch20-l7-x6",
        "level": "A2",
        "difficulty": "medium",
        "speaker": "narrator",
        "sentence": "The smallest mouse was the last help. That tiny push was the one.",
        "question": "What made the difference in the end?",
        "options": [
          "a bigger piece of rope",
          "Grandpa pulling harder",
          "the small mouse's pull",
          "the dog barking loudly"
        ],
        "optionsZh": [
          "一條更大的繩子",
          "爺爺更用力",
          "小老鼠那一拉",
          "狗大聲叫"
        ],
        "correctIndex": 2,
        "explanationZh": "「that tiny push was the one」——就是那最小的一拉改變了一切!答案是「小老鼠那一拉」。",
        "sentenceZh": "最小的老鼠是最後那個。就差她那一點點力氣。",
        "tags": [
          "story",
          "ch20",
          "enormous-turnip"
        ],
        "subSkill": "detail"
      },
      {
        "type": "listen-tf",
        "id": "kt-ch20-l7-x7",
        "level": "A2",
        "difficulty": "medium",
        "speaker": "narrator",
        "sentence": "The whole family shares a big turnip dinner. Even the mouse gets a seat.",
        "questionEn": "Is the mouse included in the celebration dinner?",
        "options": [
          "Yes",
          "No"
        ],
        "correctIndex": 0,
        "explanationZh": "「even the mouse gets a seat」——連小老鼠都有位子!答案是 Yes,大家一起慶祝!",
        "sentenceZh": "全家一起吃大蘿蔔晚餐,連小老鼠都有一個位子坐。",
        "tags": [
          "story",
          "ch20",
          "enormous-turnip",
          "inference"
        ]
      },
      {
        "type": "comprehension",
        "id": "kt-ch20-l7-x8",
        "level": "A2",
        "difficulty": "medium",
        "speaker": "narrator",
        "sentence": "The smallest mouse was the last help. That tiny push was the one.",
        "question": "What is the big lesson at the end of this story?",
        "options": [
          "mice are smarter than all others",
          "big animals do all the real work",
          "turnips are hard to pull alone",
          "small helpers matter just as much"
        ],
        "optionsZh": [
          "老鼠比所有人都聰明",
          "大動物做所有真正的工作",
          "蘿蔔很難一個人拔",
          "小幫手一樣重要"
        ],
        "correctIndex": 3,
        "explanationZh": "最小的老鼠解決了問題——故事的核心是:「小幫手一樣重要」,少了誰都不行!",
        "sentenceZh": "最小的老鼠是最後的那個。就是她那一小點力氣做到了。",
        "tags": [
          "story",
          "ch20",
          "enormous-turnip"
        ],
        "subSkill": "gist"
      }
    ]
  }
]
